njordr/__init__.py
njordr/proto.py
njordr-1.2.dist-info/METADATA
njordr-1.2.dist-info/WHEEL
njordr-1.2.dist-info/top_level.txt
njordr-1.2.dist-info/RECORD
